[{"pattern": "I need (.*)", "intent": "need"}, {"pattern": "Why don't you (.*)", "intent": "whydont"}, {"pattern": "Why can't I (.*)", "intent": "whycant"}, {"pattern": "I can't (.*)", "intent": "cant"}, {"pattern": "I am (.*)", "intent": "iam"}, {"pattern": "I'm (.*)", "intent": "im"}, {"pattern": "Are you (.*)", "intent": "areyou"}, {"pattern": "What (.*)", "intent": "what"}, {"pattern": "How (.*)", "intent": "how"}, {"pattern": "Because (.*)", "intent": "because"}, {"pattern": "(.*) sorry (.*)", "intent": "sorry"}, {"pattern": "Hello(.*)", "intent": "hello"}, {"pattern": "I think (.*)", "intent": "think"}, {"pattern": "(.*) friend(.*)", "intent": "friend"}, {"pattern": "Yes", "intent": "yes"}, {"pattern": "(.*) computer(.*)", "intent": "computer"}, {"pattern": "Is it (.*)", "intent": "isit"}, {"pattern": "It is (.*)", "intent": "itis"}, {"pattern": "Can you (.*)", "intent": "canyou"}, {"pattern": "Can I (.*)", "intent": "cani"}, {"pattern": "You are (.*)", "intent": "you're"}, {"pattern": "You're (.*)", "intent": "you're"}, {"pattern": "I don't (.*)", "intent": "dont"}, {"pattern": "I feel (.*)", "intent": "feel"}, {"pattern": "I have (.*)", "intent": "have"}, {"pattern": "I would (.*)", "intent": "would"}, {"pattern": "Is there (.*)", "intent": "is"}, {"pattern": "My (.*)", "intent": "my"}, {"pattern": "You (.*)", "intent": "you"}, {"pattern": "Why (.*)", "intent": "why"}, {"pattern": "I want (.*)", "intent": "want"}, {"pattern": "(.*) mother(.*)", "intent": "mother"}, {"pattern": "(.*) father(.*)", "intent": "father"}, {"pattern": "(.*) child(.*)", "intent": "child"}, {"pattern": "(.*)\\?", "intent": "why"}, {"pattern": "quit", "intent": "quit"}, {"pattern": "(.*)", "intent": "more"}]